{
  "date": "2026-06-17",
  "strategy": "momentum+trailing",
  "picks": [
    {
      "symbol": "HOOD",
      "price": 105.19,
      "pct": 8.28,
      "vol_m": 2.0,
      "score": 8.28
    },
    {
      "symbol": "INTC",
      "price": 121.08,
      "pct": 7.35,
      "vol_m": 4.1,
      "score": 7.35
    },
    {
      "symbol": "MARA",
      "price": 13.925,
      "pct": 6.91,
      "vol_m": 1.4,
      "score": 6.91
    },
    {
      "symbol": "ROKU",
      "price": 137.3,
      "pct": 6.54,
      "vol_m": 0.7,
      "score": 6.54
    },
    {
      "symbol": "AFRM",
      "price": 70.7,
      "pct": 6.46,
      "vol_m": 0.3,
      "score": 6.46
    },
    {
      "symbol": "RIVN",
      "price": 16.25,
      "pct": 6.24,
      "vol_m": 1.5,
      "score": 6.24
    },
    {
      "symbol": "RIOT",
      "price": 27.43,
      "pct": 6.2,
      "vol_m": 0.4,
      "score": 6.2
    },
    {
      "symbol": "CVNA",
      "price": 62.855,
      "pct": 5.79,
      "vol_m": 1.1,
      "score": 5.79
    },
    {
      "symbol": "DKNG",
      "price": 26.32,
      "pct": 5.6,
      "vol_m": 0.8,
      "score": 5.6
    },
    {
      "symbol": "CCL",
      "price": 29.92,
      "pct": 5.32,
      "vol_m": 1.9,
      "score": 5.32
    }
  ]
}
